tesla/__init__.py
tesla/admin/__init__.py
tesla/admin/collections.py
tesla/admin/forms.py
tesla/admin/middleware.py
tesla/admin/models.py
tesla/admin/urls.py
tesla/admin/views.py
tesla/admin/statics/__
tesla/admin/statics/admin/assets/.DS_Store
tesla/admin/statics/admin/assets/css/.DS_Store
tesla/admin/statics/admin/assets/css/portal.css
tesla/admin/statics/admin/assets/images/.DS_Store
tesla/admin/statics/admin/assets/js/.DS_Store
tesla/admin/statics/admin/assets/js/app.js
tesla/admin/statics/admin/assets/js/charts-demo.js
tesla/admin/statics/admin/assets/js/index-charts.js
tesla/admin/statics/admin/assets/plugins/.DS_Store
tesla/admin/statics/admin/assets/plugins/popper.min.js
tesla/admin/statics/admin/assets/plugins/bootstrap/.DS_Store
tesla/admin/statics/admin/assets/plugins/bootstrap/js/bootstrap.bundle.js
tesla/admin/statics/admin/assets/plugins/bootstrap/js/bootstrap.bundle.js.map
tesla/admin/statics/admin/assets/plugins/bootstrap/js/bootstrap.bundle.min.js
tesla/admin/statics/admin/assets/plugins/bootstrap/js/bootstrap.bundle.min.js.map
tesla/admin/statics/admin/assets/plugins/bootstrap/js/bootstrap.esm.js
tesla/admin/statics/admin/assets/plugins/bootstrap/js/bootstrap.esm.js.map
tesla/admin/statics/admin/assets/plugins/bootstrap/js/bootstrap.esm.min.js
tesla/admin/statics/admin/assets/plugins/bootstrap/js/bootstrap.esm.min.js.map
tesla/admin/statics/admin/assets/plugins/bootstrap/js/bootstrap.js
tesla/admin/statics/admin/assets/plugins/bootstrap/js/bootstrap.js.map
tesla/admin/statics/admin/assets/plugins/bootstrap/js/bootstrap.min.js
tesla/admin/statics/admin/assets/plugins/bootstrap/js/bootstrap.min.js.map
tesla/admin/statics/admin/assets/plugins/fontawesome/.DS_Store
tesla/admin/statics/admin/assets/plugins/fontawesome/js/all.js
tesla/admin/statics/admin/assets/plugins/fontawesome/js/all.min.js
tesla/admin/templates/__init__.py
tesla/admin/templates/admin/__init__.py
tesla/admin/templates/admin/account.html
tesla/admin/templates/admin/base_admin.html
tesla_web-0.0.3.8.dist-info/METADATA
tesla_web-0.0.3.8.dist-info/WHEEL
tesla_web-0.0.3.8.dist-info/top_level.txt
tesla_web-0.0.3.8.dist-info/RECORD
