Metadata-Version: 2.1
Name: tesla-web
Version: 0.0.3.8
Summary: A flexiable web framework
Home-page: UNKNOWN
Author: Jafar idris
Author-email: <jafaridris82@gmail.com>
License: UNKNOWN
Keywords: python,web,auth
Platform: UNKNOWN
Classifier: Development Status :: 1 - Planning
Classifier: Intended Audience :: Developers
Classifier: Programming Language :: Python :: 3
Classifier: Operating System :: Unix
Classifier: Operating System :: MacOS :: MacOS X
Classifier: Operating System :: Microsoft :: Windows
Requires-Dist: uuid
Requires-Dist: jinja2
Requires-Dist: tesla-admin
Requires-Dist: argon2-cffi
Requires-Dist: waitress
